haystack_integrations/components/generators/py.typed
haystack_integrations/components/generators/aimlapi/__init__.py
haystack_integrations/components/generators/aimlapi/chat/__init__.py
haystack_integrations/components/generators/aimlapi/chat/chat_generator.py
aimlapi_haystack-2.0.0.dist-info/METADATA
aimlapi_haystack-2.0.0.dist-info/WHEEL
aimlapi_haystack-2.0.0.dist-info/licenses/LICENSE.txt
aimlapi_haystack-2.0.0.dist-info/RECORD
